puf/__init__.py
puf/cli.py
puf/core.py
puf_cli-0.2.0.dist-info/METADATA
puf_cli-0.2.0.dist-info/WHEEL
puf_cli-0.2.0.dist-info/entry_points.txt
puf_cli-0.2.0.dist-info/top_level.txt
puf_cli-0.2.0.dist-info/RECORD
